kafkaSchemaManager/__init__.py
kafkaSchemaManager/abstract/AbstractDatabaseConfig.py
kafkaSchemaManager/abstract/AbstractDatabaseSchemaOperations.py
kafkaSchemaManager/abstract/AbstractKafkaAvroProducer.py
kafkaSchemaManager/abstract/AbstractKafkaConfig.py
kafkaSchemaManager/abstract/AbstractKafkaSchemaRegistryUpdater.py
kafkaSchemaManager/abstract/AbstractLocalSchemaLoader.py
kafkaSchemaManager/abstract/AbstractObjectSerializer.py
kafkaSchemaManager/abstract/AbstractSchemaHolder.py
kafkaSchemaManager/abstract/AbstractSchemaSaver.py
kafkaSchemaManager/abstract/__init__.py
kafkaSchemaManager/builders/__init__.py
kafkaSchemaManager/builders/commandCenterBuilder.py
kafkaSchemaManager/builders/commandCenterInstanceManager.py
kafkaSchemaManager/decorator/CommandCenterFactory.py
kafkaSchemaManager/decorator/__init__.py
kafkaSchemaManager/decorator/commandCenter.py
kafkaSchemaManager/decorator/commandCenterEnum.py
kafkaSchemaManager/implementation/__init__.py
kafkaSchemaManager/implementation/config/JsonKafkaConfig.py
kafkaSchemaManager/implementation/config/SimpleKafkaConfig.py
kafkaSchemaManager/implementation/config/__init__.py
kafkaSchemaManager/implementation/config/postgreSqlDevConfig.py
kafkaSchemaManager/implementation/config/postgreSqlLocalConfig.py
kafkaSchemaManager/implementation/helpers/DictionarySerializerMethod.py
kafkaSchemaManager/implementation/helpers/JsonFileSaver.py
kafkaSchemaManager/implementation/helpers/JsonObjectSerializer.py
kafkaSchemaManager/implementation/helpers/__init__.py
kafkaSchemaManager/implementation/kafka/KafkaAvroProducer.py
kafkaSchemaManager/implementation/kafka/KafkaSchemaRegistryUpdater.py
kafkaSchemaManager/implementation/kafka/__init__.py
kafkaSchemaManager/implementation/localSchema/DummyLocalSchemaSaver.py
kafkaSchemaManager/implementation/localSchema/JsonLocalSchemaLoader.py
kafkaSchemaManager/implementation/localSchema/LocalSchemaHolder.py
kafkaSchemaManager/implementation/localSchema/LocalSchemaHolderFactory.py
kafka_avro_producer_topkrabbensteam-1.3.1.dist-info/LICENSE
kafka_avro_producer_topkrabbensteam-1.3.1.dist-info/METADATA
kafka_avro_producer_topkrabbensteam-1.3.1.dist-info/WHEEL
kafka_avro_producer_topkrabbensteam-1.3.1.dist-info/top_level.txt
kafka_avro_producer_topkrabbensteam-1.3.1.dist-info/RECORD
