Metadata-Version: 2.1
Name: kafka-avro-producer-topkrabbensteam
Version: 1.3.1
Summary: Kafka (produce messages) using Apache Avro schemas
Home-page: https://github.com/YendiyarovSV/kafka-avro-producer-topkrabbensteam
Author: Sergei Yendiyarov
Author-email: s.endiyarov@gmail.com
License: License :: OSI Approved :: Apache Software License
Requires-Dist: datamountaineer-schemaregistry (==0.3)
Requires-Dist: avro-gen-topkrabbensteam (==0.0.2)
Requires-Dist: fastavro (==0.14.11)
Requires-Dist: kafka-python (==1.4.3)
Requires-Dist: psycopg2 (==2.7.5)
Requires-Dist: SQLAlchemy (==1.2.10)
Requires-Dist: avro (>=1.8.0); python_version < "3.0"
Requires-Dist: avro-python3 (>=1.8.0); python_version > "3.0"
